naver_db/__init__.py
naver_db/persistence.py
test/__init__.py
test/naver_getprops.py
test/naver_nextval.py
test/naver_param.py
test/naver_query.py
test/naver_userpermission.py
test/naver_write.py
test/naver_writelog.py
naver_db-0.0.5.post14.dist-info/METADATA
naver_db-0.0.5.post14.dist-info/WHEEL
naver_db-0.0.5.post14.dist-info/top_level.txt
naver_db-0.0.5.post14.dist-info/RECORD
