Metadata-Version: 2.1
Name: naver-db
Version: 0.0.5.post14
Summary: A DB Persistence Ancestor Library
Home-page: https://github.com/jacr6/naver-db
Author: Jose Cuevas
Author-email: jose.cuevas.cv@gmail.com
Classifier: Programming Language :: Python :: 3
Classifier: License :: OSI Approved :: MIT License
Classifier: Operating System :: OS Independent
Requires-Dist: Flask-SQLAlchemy
Requires-Dist: naver-config
Requires-Dist: psycopg2
Requires-Dist: pickledb
Requires-Dist: redis
